.gitignore
CONTRIBUTING.md
LICENSE
Makefile
README.md
pyproject.toml
requirements-dev.txt
requirements.txt
setup.py
.github/ISSUE_TEMPLATE/bug_report.md
.github/ISSUE_TEMPLATE/feature_request.md
.github/workflows/build-test.yml
.github/workflows/building-pypi-linux.yml
.github/workflows/docs.yml
data/source_mesh.vtk
data/source_mesh_15k.vtk
data/target_mesh.vtk
data/target_mesh_15k.vtk
docs/eigsort.html
docs/focusr.html
docs/graph.html
docs/index.html
docs/main.html
docs/test.html
docs/vtk_functions.html
examples/Example_registering_two_bone_meshes.ipynb
examples/Notebook_for_testing_and_comparing_features.ipynb
images/average_mesh.png
images/eig_vec_1_fiedler.png
images/eig_vec_2.png
images/eig_vec_3.png
images/ezgif.com-gif-maker.gif
images/mesh_transformed_to_target.png
images/source.png
images/target.png
pyfocusr/__init__.py
pyfocusr/eigsort.py
pyfocusr/focusr.py
pyfocusr/graph.py
pyfocusr/main.py
pyfocusr/test.py
pyfocusr/vtk_functions.py
pyfocusr.egg-info/PKG-INFO
pyfocusr.egg-info/SOURCES.txt
pyfocusr.egg-info/dependency_links.txt
pyfocusr.egg-info/top_level.txt
pyfocusr/__pycache__/__init__.cpython-38.pyc
pyfocusr/__pycache__/eigsort.cpython-38.pyc
pyfocusr/__pycache__/focusr.cpython-38.pyc
pyfocusr/__pycache__/graph.cpython-38.pyc
pyfocusr/__pycache__/main.cpython-38.pyc
pyfocusr/__pycache__/vtk_functions.cpython-38.pyc
testing/fake_test.py